aerisweather/__init__.py
aerisweather/aerisweather.py
aerisweather/doxygen_main_page.py
aerisweather/version.py
aerisweather/requests/Endpoint.py
aerisweather/requests/ParameterType.py
aerisweather/requests/RequestAction.py
aerisweather/requests/RequestFilter.py
aerisweather/requests/RequestLocation.py
aerisweather/requests/RequestQuery.py
aerisweather/requests/RequestSort.py
aerisweather/requests/__init__.py
aerisweather/responses/AerisLocation.py
aerisweather/responses/AerisPlace.py
aerisweather/responses/AerisProfile.py
aerisweather/responses/AerisRelativeTo.py
aerisweather/responses/AlertDetails.py
aerisweather/responses/AlertIncludes.py
aerisweather/responses/AlertTimestamps.py
aerisweather/responses/AlertsResponse.py
aerisweather/responses/ConditionsPeriod.py
aerisweather/responses/ConditionsResponse.py
aerisweather/responses/CustomResponse.py
aerisweather/responses/ForecastPeriod.py
aerisweather/responses/ForecastsResponse.py
aerisweather/responses/ObservationsData.py
aerisweather/responses/ObservationsResponse.py
aerisweather/responses/ObservationsSummaryDewPt.py
aerisweather/responses/ObservationsSummaryPeriod.py
aerisweather/responses/ObservationsSummaryPrecip.py
aerisweather/responses/ObservationsSummaryPressure.py
aerisweather/responses/ObservationsSummaryQC.py
aerisweather/responses/ObservationsSummaryRange.py
aerisweather/responses/ObservationsSummaryRelativeHumidity.py
aerisweather/responses/ObservationsSummaryResponse.py
aerisweather/responses/ObservationsSummarySky.py
aerisweather/responses/ObservationsSummarySolrad.py
aerisweather/responses/ObservationsSummaryStationPressure.py
aerisweather/responses/ObservationsSummaryTemp.py
aerisweather/responses/ObservationsSummaryVisibility.py
aerisweather/responses/ObservationsSummaryWeather.py
aerisweather/responses/ObservationsSummaryWind.py
aerisweather/responses/PlacesResponse.py
aerisweather/responses/Response.py
aerisweather/responses/RiversCategories.py
aerisweather/responses/RiversCrests.py
aerisweather-0.4.1.dist-info/LICENSE
aerisweather-0.4.1.dist-info/METADATA
aerisweather-0.4.1.dist-info/WHEEL
aerisweather-0.4.1.dist-info/top_level.txt
aerisweather-0.4.1.dist-info/RECORD
