Metadata-Version: 2.1
Name: aerisweather
Version: 0.4.1
Summary: The AerisWeather Python SDK allows a developer to quickly and easily add weather content and functionality to their Python applications.
Home-page: https://aerisweather.com
Author: AerisWeather
Author-email: pypi@aerisweather.com
License: MIT
Platform: UNKNOWN
Requires-Dist: aenum (>=3.0.0)
